README.rst
setup.cfg
setup.py
poli_enum/__init__.py
poli_enum/continent.py
poli_enum/country.py
poli_enum/currency.py
poli_enum/layout.py
poli_enum/subdivision.py
poli_enum.egg-info/PKG-INFO
poli_enum.egg-info/SOURCES.txt
poli_enum.egg-info/dependency_links.txt
poli_enum.egg-info/requires.txt
poli_enum.egg-info/top_level.txt