Metadata-Version: 2.1
Name: poli-enum
Version: 1.0
Summary: Political enums: continent, country (ISO 3166-1), subdivision (ISO 3166-2), currency (ISO 4217) and keyboard layouts (debian).
Home-page: https://github.com/bustawin/poli-enum
Author: Xavier Bustamante Talavera
Author-email: xavier@bustawin.com
License: AGPLV3
Project-URL: Documentation, https://github.com/bustawin/poli-enum
Project-URL: Code, https://github.com/bustawin/poli-enum
Project-URL: Issue tracker, https://github.com/bustawin/poli-enum/issues
Platform: UNKNOWN
Classifier: Development Status :: 5 - Production/Stable
Classifier: Intended Audience :: Developers
Classifier: License :: OSI Approved :: GNU Affero General Public License v3
Classifier: Operating System :: OS Independent
Classifier: Programming Language :: Python :: 3 :: Only
Classifier: Programming Language :: Python :: 3.6
Classifier: Programming Language :: Python :: 3.7
Classifier: Programming Language :: Python :: 3.8
Classifier: Topic :: Database
Classifier: Topic :: Software Development :: Libraries :: Python Modules
Requires-Python: >=3.6
Provides-Extra: test
